spz-0.0.1.dist-info/METADATA
spz-0.0.1.dist-info/WHEEL
spz/__init__.py
spz/__pycache__/__init__.cpython-313.pyc
spz/__pycache__/context_managers.cpython-313.pyc
spz/__pycache__/extra.cpython-313.pyc
spz/context_managers.py
spz/py.typed
spz/spz.cpython-313-x86_64-linux-gnu.so
spz/spz.pyi
spz-0.0.1.dist-info/RECORD
