Metadata-Version: 2.4
Name: spz
Version: 0.0.1
Classifier: Intended Audience :: Developers
Classifier: Intended Audience :: Science/Research
Classifier: License :: OSI Approved :: MIT License
Classifier: Operating System :: OS Independent
Classifier: Programming Language :: Python :: 3
Classifier: Programming Language :: Python :: 3.8
Classifier: Programming Language :: Python :: 3.9
Classifier: Programming Language :: Python :: 3.10
Classifier: Programming Language :: Python :: 3.11
Classifier: Programming Language :: Python :: 3.12
Classifier: Programming Language :: Python :: 3.13
Classifier: Programming Language :: Rust
Classifier: Programming Language :: Python :: Implementation :: CPython
Classifier: Programming Language :: Python :: Implementation :: PyPy
Classifier: Topic :: Multimedia :: Graphics :: 3D Modeling
Classifier: Topic :: Scientific/Engineering :: Visualization
Requires-Dist: numpy>=1.20
Provides-Extra: dev
Summary: SPZ file format handling for Python (in Rust).
Keywords: gaussian-splatting,point-cloud,3d,graphics,compression,spz
Home-Page: https://github.com/Jackneill/spz
Author: See AUTHORS.md
License: MIT OR Apache-2.0
Requires-Python: >=3.8
Project-URL: Homepage, https://github.com/Jackneill/spz
Project-URL: Repository, https://github.com/Jackneill/spz.git
Project-URL: Documentation, https://github.com/Jackneill/spz#readme
Project-URL: Issues, https://github.com/Jackneill/spz/issues
